psyplot/__init__.py
psyplot/__main__.py
psyplot/_version.py
psyplot/data.py
psyplot/docstring.py
psyplot/gdal_store.py
psyplot/plotter.py
psyplot/project.py
psyplot/utils.py
psyplot/warning.py
psyplot/config/__init__.py
psyplot/config/logsetup.py
psyplot/config/rcsetup.py
psyplot/sphinxext/__init__.py
psyplot/sphinxext/extended_napoleon.py
psyplot-1.5.1.dist-info/CC-BY-4.0.txt
psyplot-1.5.1.dist-info/CC0-1.0.txt
psyplot-1.5.1.dist-info/LGPL-3.0-only.txt
psyplot-1.5.1.dist-info/METADATA
psyplot-1.5.1.dist-info/WHEEL
psyplot-1.5.1.dist-info/entry_points.txt
psyplot-1.5.1.dist-info/top_level.txt
psyplot-1.5.1.dist-info/RECORD
