Metadata-Version: 2.1
Name: psyplot
Version: 1.5.1
Summary: Python package for interactive data visualization
Author-email: "Philipp S. Sommer" <philipp.sommer@hereon.de>
Maintainer-email: "Philipp S. Sommer" <philipp.sommer@hereon.de>
License: LGPL-3.0-only
Project-URL: Homepage, https://codebase.helmholtz.cloud/psyplot/psyplot
Project-URL: Documentation, https://psyplot.github.io
Project-URL: Source, https://codebase.helmholtz.cloud/psyplot/psyplot
Project-URL: Tracker, https://codebase.helmholtz.cloud/psyplot/psyplot/issues/
Keywords: visualization,netcdf,raster,cartopy,earth-sciences
Classifier: Development Status :: 5 - Production/Stable
Classifier: Intended Audience :: Developers
Classifier: Topic :: Scientific/Engineering :: Visualization
Classifier: Topic :: Scientific/Engineering :: GIS
Classifier: Topic :: Scientific/Engineering
Classifier: License :: OSI Approved :: GNU Lesser General Public License v3 (LGPLv3)
Classifier: Programming Language :: Python :: 3
Classifier: Programming Language :: Python :: 3 :: Only
Classifier: Programming Language :: Python :: 3.9
Classifier: Programming Language :: Python :: 3.10
Classifier: Programming Language :: Python :: 3.11
Classifier: Programming Language :: Python :: 3.12
Classifier: Operating System :: OS Independent
Requires-Python: >=3.9
License-File: LICENSES/CC-BY-4.0.txt
License-File: LICENSES/CC0-1.0.txt
License-File: LICENSES/LGPL-3.0-only.txt
Requires-Dist: matplotlib
Requires-Dist: docrep >=0.3
Requires-Dist: funcargparse
Requires-Dist: xarray >=0.17
Requires-Dist: PyYAML >=4.2b
Provides-Extra: dev
Requires-Dist: psyplot[testsite] ; extra == 'dev'
Requires-Dist: psyplot[docs] ; extra == 'dev'
Requires-Dist: PyYAML ; extra == 'dev'
Requires-Dist: types-PyYAML ; extra == 'dev'
Provides-Extra: docs
Requires-Dist: autodocsumm ; extra == 'docs'
Requires-Dist: sphinx-rtd-theme ; extra == 'docs'
Requires-Dist: hereon-netcdf-sphinxext ; extra == 'docs'
Requires-Dist: sphinx-design ; extra == 'docs'
Requires-Dist: ipython ; extra == 'docs'
Requires-Dist: pickleshare ; extra == 'docs'
Requires-Dist: seaborn ; extra == 'docs'
Requires-Dist: dask ; extra == 'docs'
Requires-Dist: netCDF4 ; extra == 'docs'
Requires-Dist: sphinx-argparse ; extra == 'docs'
Requires-Dist: cdo ; extra == 'docs'
Requires-Dist: cookiecutter ; extra == 'docs'
Requires-Dist: GitPython ; extra == 'docs'
Requires-Dist: pre-commit ; extra == 'docs'
Requires-Dist: reuse ; extra == 'docs'
Provides-Extra: testsite
Requires-Dist: tox ; extra == 'testsite'
Requires-Dist: isort ==5.12.0 ; extra == 'testsite'
Requires-Dist: black ==23.1.0 ; extra == 'testsite'
Requires-Dist: blackdoc ==0.3.8 ; extra == 'testsite'
Requires-Dist: flake8 ==6.0.0 ; extra == 'testsite'
Requires-Dist: pre-commit ; extra == 'testsite'
Requires-Dist: mypy ; extra == 'testsite'
Requires-Dist: pytest-cov ; extra == 'testsite'
Requires-Dist: reuse ; extra == 'testsite'
Requires-Dist: cffconvert ; extra == 'testsite'
Requires-Dist: pytest-xdist ; extra == 'testsite'
Requires-Dist: netCDF4 ; extra == 'testsite'
Requires-Dist: dask ; extra == 'testsite'
Requires-Dist: scipy ; extra == 'testsite'
Requires-Dist: pytest ; extra == 'testsite'
